tauripy/__init__.py
tauripy/libtauric.dylib
tauripy-0.1.0b11.dist-info/METADATA
tauripy-0.1.0b11.dist-info/WHEEL
tauripy-0.1.0b11.dist-info/RECORD
