Metadata-Version: 2.4
Name: tauripy
Version: 0.1.0b11
Summary: Create tauri desktop app in Python
Project-URL: Repository, https://github.com/thewh1teagle/tauric
Author-email: thewh1teagle <61390950+thewh1teagle@users.noreply.github.com>
Requires-Python: >=3.6
